libHalf.so.24
libblosc.so.1
libboost_iostreams.so.1.68.0
libboost_numpy38.so.1.68.0
libboost_python38.so.1.68.0
liblog4cplus-1.1.so.9
libm.so.6
libopenvdb.so.7.2
libsnappy.so.1
libtbb.so.2
libtbbmalloc.so.2
libtbbmalloc_proxy.so.2
libzstd.so.1.4.4
pyopenvdb.so
openvdb/__init__.py
pyopenvdb_3.8-0.1.5.dist-info/LICENSE
pyopenvdb_3.8-0.1.5.dist-info/METADATA
pyopenvdb_3.8-0.1.5.dist-info/WHEEL
pyopenvdb_3.8-0.1.5.dist-info/top_level.txt
pyopenvdb_3.8-0.1.5.dist-info/RECORD
